order_matching/__init__.py
order_matching/custom_enum.py
order_matching/executed_trades.py
order_matching/execution.py
order_matching/matching_engine.py
order_matching/order.py
order_matching/order_book.py
order_matching/orders.py
order_matching/random.py
order_matching/schemas.py
order_matching/side.py
order_matching/status.py
order_matching/trade.py
order_matching-0.3.12.dist-info/LICENSE
order_matching-0.3.12.dist-info/METADATA
order_matching-0.3.12.dist-info/WHEEL
order_matching-0.3.12.dist-info/top_level.txt
order_matching-0.3.12.dist-info/RECORD
