Metadata-Version: 2.2
Name: order-matching
Version: 0.3.12
Summary: Order Book Matching Engine
Author-email: Stanislav Khrapov <khrapovs@gmail.com>, Akanksha Toshniwal <akanksha.toshniwal@chintai.io>, Shannen Tioniwar <shannen.tioniwar@chintai.io>
Project-URL: Source, https://github.com/khrapovs/OrderBookMatchingEngine
Project-URL: Documentation, https://order-book-matching-engine.readthedocs.io/
Classifier: Programming Language :: Python
Classifier: Programming Language :: Python :: 3.10
Classifier: Programming Language :: Python :: 3.11
Classifier: Programming Language :: Python :: 3.12
Classifier: Programming Language :: Python :: 3.13
Requires-Python: >=3.10
License-File: LICENSE
Requires-Dist: pandas
Requires-Dist: pandera
Requires-Dist: faker
Provides-Extra: test
Requires-Dist: pytest; extra == "test"
Requires-Dist: pytest-cov; extra == "test"
Requires-Dist: pytest-xdist; extra == "test"
Requires-Dist: pytest-benchmark[histogram]; extra == "test"
Provides-Extra: doc
Requires-Dist: mkdocs-material; extra == "doc"
Requires-Dist: mkdocstrings[python]; extra == "doc"
Requires-Dist: mkdocs-gen-files; extra == "doc"
Requires-Dist: mkdocs-literate-nav; extra == "doc"
Requires-Dist: mkdocs-macros-plugin; extra == "doc"
Requires-Dist: pymdown-extensions; extra == "doc"
Provides-Extra: dev
Requires-Dist: pre-commit; extra == "dev"
